{
    "url": "https://en.wikipedia.org/wiki/Go_and_Get_It",
    "title": "Go and Get It",
    "summary": "Go and Get It is a 1920 American silent comedy-drama mystery film directed by Marshall Neilan and Henry Roberts Symonds and written by Marion Fairfax.  The film stars Pat O'Malley, Wesley Barry, Noah Beery Sr. and Agnes Ayres. The cinematographer was David Kesson. The film was released on July 18, 1920 by First National Exhibitors' Circuit.Actor Bull Montana (a former professional wrestler) played Ferry, the Ape Creature, in the film. He later went on to play the ape-man in the 1925 Willis H. O'Brien classic The Lost World, which was also written by Marion Fairfax and starred Noah Beery's actor brother Wallace Beery.",
    "content": "Go and Get It is a 1920 American silent comedy-drama mystery film directed by Marshall Neilan and Henry Roberts Symonds and written by Marion Fairfax.  The film stars Pat O'Malley, Wesley Barry, Noah Beery Sr. and Agnes Ayres. The cinematographer was David Kesson. The film was released on July 18, 1920 by First National Exhibitors' Circuit.Actor Bull Montana (a former professional wrestler) played Ferry, the Ape Creature, in the film. He later went on to play the ape-man in the 1925 Willis H. O'Brien classic The Lost World, which was also written by Marion Fairfax and starred Noah Beery's actor brother Wallace Beery.\n\n\n== Plot ==\nHelen Allen (Agnes Ayres) inherits her deceased father's newspaper, but someone is trying to sabotage the business. She gets a job at the company under a false name, so that she can detect exactly who is trying to ruin her. She winds up instead investigating a number of gruesome murders with the help of a reporter named Kirk Connelly (Pat O'Malley).\nOne of the victims was a scientist named Dr. Ord (Noah Beery). Helen learns that Dr. Ord had been involved in an experiment in which he transplanted the brain of a criminal into the body of a gorilla. The beast turned on him and then went on a killing spree, hunting down and murdering all of his old enemies. In the end, Helen also finds out who it was who was trying to ruin her newspaper.\n\n\n== Cast ==\nPat O'Malley as Kirk Connelly\nWesley Barry as Dinty\nAgnes Ayres as Helen Allen\nJ. Barney Sherry as 'Shut the Door' Gordon\nCharles Hill Mailes as J.L. Rich\nNoah Beery Sr. as Dr. Ord\nBull Montana as Ferry the ape creature\nWalter Long as Jim Hogan\nLydia Yeamans Titus as Lilly Doody\nGeorge Dromgold as Thomas Hickson\nEdward Cooper as W.W. Crocker\nCharles West as Slim Hogan\nSamuel G. Blythe\nMyles Lasker\nRing Lardner\nIrvin S. Cobb\nArthur Brisbane\nRobert Edgren\nFred L. Wilson\n\n\n== Preservation ==\nThe film was considered a lost film for decades. A print was discovered at the Cineteca Italiana film archive in Italy.\n\n\n== References ==\n\n\n== External links ==\nGo and Get It at IMDb",
    "links": [
        "A Little Princess (1917 film)",
        "Agnes Ayres",
        "Amarilly of Clothes-Line Alley",
        "Arthur Brisbane",
        "Bits of Life",
        "Bob Hampton of Placer",
        "Bull Montana",
        "Charles Hill Mailes",
        "Charles West (actor)",
        "Chloe, Love Is Calling You",
        "Cineteca Italiana",
        "Comedy-drama",
        "Comedy-drama film",
        "Daddy-Long-Legs (1919 film)",
        "Dinty (film)",
        "Diplomacy (1926 film)",
        "Don't Ever Marry",
        "Dorothy Vernon of Haddon Hall (film)",
        "Edward Cooper (actor)",
        "Everybody's Acting",
        "First National Pictures",
        "Fools First",
        "George Dromgold",
        "Heart of the Wilds",
        "Her Kingdom of Dreams",
        "Her Wild Oat",
        "His Last Haul",
        "Hit-The-Trail Holliday",
        "IMDb",
        "ISBN (identifier)",
        "In Old Kentucky (1919 film)",
        "Irvin S. Cobb",
        "J. Barney Sherry",
        "Lost film",
        "Lydia Yeamans Titus",
        "M'Liss (1918 film)",
        "Marion Fairfax",
        "Marshall Neilan",
        "Mike (film)",
        "Minnie (film)",
        "Mystery film",
        "Noah Beery",
        "Noah Beery Sr.",
        "Out of a Clear Sky",
        "Pat O'Malley (actor)",
        "Penrod (film)",
        "Rebecca of Sunnybrook Farm (1917 film)",
        "Sing While You're Able",
        "Social Register (film)",
        "Stella Maris (1918 film)",
        "Sweethearts on Parade (1930 film)",
        "Swing It, Professor",
        "Take Me Home (1928 film)",
        "Tanned Legs",
        "Taxi 13",
        "Tess of the d'Urbervilles (1924 film)",
        "Thanks for Listening (film)",
        "The Awful Truth (1929 film)",
        "The Bottle Imp (1917 film)",
        "The Deadly Battle at Hicksville",
        "The Eternal Three",
        "The Great Love (1925 film)",
        "The Lemon Drop Kid (1934 film)",
        "The Lost World (1925 film)",
        "The Lotus Eater (film)",
        "The Rendezvous (1923 film)",
        "The Silent Partner (1917 film)",
        "The Skyrocket",
        "The Sporting Venus",
        "The Strangers' Banquet",
        "The Unpardonable Sin",
        "The Vagabond Lover",
        "This Is the Life (1935 film)",
        "Three-Ring Marriage",
        "Three Men and a Girl",
        "Venus of Venice",
        "Wallace Beery",
        "Walter Long (actor)",
        "Wesley Barry",
        "Wild Oats Lane",
        "Willis H. O'Brien"
    ]
}