{"url": "https://en.wikipedia.org/wiki/Neric_Wei", "title": "Neric Wei", "summary": "Chao Yin \"Neric\" Wei (born 21 March 1981) is a Chinese racing driver currently competing in the TCR International Series and TCR Asia Series. Having previously competed in the Asian Le Mans Series Sprint Cup, Asian Formula Renault Series and Lotus Interport Cup Series amongst others.\n\n", "content": "Chao Yin \"Neric\" Wei (born 21 March 1981) is a Chinese racing driver currently competing in the TCR International Series and TCR Asia Series. Having previously competed in the Asian Le Mans Series Sprint Cup, Asian Formula Renault Series and Lotus Interport Cup Series amongst others.\n\n\n== Racing career ==\nWei began his career in 2010 in the Zhuhai Pan Delta Super Racing Festival, he won the championship three years in a row, from 2010-2012. He switched to the Lotus Interport Cup Series in 2013 and won the title that year. He also raced in the Asian Formula Renault Series in 2013, finishing fifth in the championship standings that year. He also took part in the Macau Lotus Greater China Race that year. For 2014 he returned to the Asian Formula Renault Series, finishing third in the championship that year. He stayed there for 2015, finishing twelfth in the standings. He switched to the new Asian Le Mans Series Sprint Cup for 2016, winning the CN class that season. He switched to the TCR Asia Series following his season in the Asian Le Mans Series Sprint Cup, joining the series at the third round held in Shanghai.In September 2016 it was announced that he would race in the TCR International Series, driving a Volkswagen Golf GTI TCR for Son Veng Racing Team.\n\n\n== Racing record ==\n\n\n=== Complete TCR International Series results ===\n(key) (Races in bold indicate pole position) (Races in italics indicate fastest lap)\n\n† Driver did not finish the race, but was classified as he completed over 90% of the race distance.\n\n\n=== TCR Spa 500 results ===\n\n\n== References ==\n\n\n== External links ==\nNeric Wei career summary at DriverDB.com", "links": ["2013 Asian Formula Renault Series", "2015 Asian Formula Renault Series", "2016 TCR Asia Series", "2016 TCR International Series season", "2019 TCR Spa 500", "Andy Yan", "Asian Formula Renault Series", "Audi A3", "Autodromo Enzo e Dino Ferrari", "Autódromo do Estoril", "Bahrain International Circuit", "Chang International Circuit", "China", "Chinese name", "Chinese surname", "Circuit de Spa-Francorchamps", "Guangdong", "Guia Circuit", "Hong Kong", "Marina Bay Street Circuit", "Motorsport Arena Oschersleben", "Salzburgring", "Sepang International Circuit", "Sochi Autodrom", "Son Veng Racing Team", "TCR Asia Series", "TCR International Series", "Teamwork Motorsport", "Volkswagen Golf Mk7", "Wei (surname)"]}