{"url": "https://en.wikipedia.org/wiki/Villa_Elfvik", "title": "Villa Elfvik", "summary": "The Villa Elfvik nature house is an environmental education centre in Espoo, Finland, directed at all residents of Espoo. The nature house offers information about nature and the environment in all forms.\nJugend style Villa Elfvik was designed by the architect Mauritz Gripenberg. The construction project finished in 1904. The villa was built to be a home for baroness Elvira Standertskjöld.Villa Elfvik is located in Laajalahti near the seashore, between the commercial centres of Tapiola and Leppävaara.", "content": "The Villa Elfvik nature house is an environmental education centre in Espoo, Finland, directed at all residents of Espoo. The nature house offers information about nature and the environment in all forms.\nJugend style Villa Elfvik was designed by the architect Mauritz Gripenberg. The construction project finished in 1904. The villa was built to be a home for baroness Elvira Standertskjöld.Villa Elfvik is located in Laajalahti near the seashore, between the commercial centres of Tapiola and Leppävaara.\n\n\n== References ==\n\n\n== External links ==\n Media related to Villa Elfvik at Wikimedia Commons\nVilla Elfvik nature house, City of Espoo.\nPictures from the Villa Elfvik area", "links": ["Espoo", "Finland", "Geographic coordinate system", "Jugend style", "Laajalahti", "Leppävaara", "Tapiola"]}